moteus_pi3hat/__init__.py
moteus_pi3hat/_pi3hat_device.so
moteus_pi3hat/pi3hat_device.py
moteus_pi3hat-0.3.33.dist-info/METADATA
moteus_pi3hat-0.3.33.dist-info/WHEEL
moteus_pi3hat-0.3.33.dist-info/entry_points.txt
moteus_pi3hat-0.3.33.dist-info/top_level.txt
moteus_pi3hat-0.3.33.dist-info/RECORD
