Metadata-Version: 2.1
Name: moteus-pi3hat
Version: 0.3.33
Summary: moteus brushless controller library and tools
Home-page: https://github.com/mjbots/pi3hat
Author: mjbots Robotic Systems
Author-email: info@mjbots.com
Keywords: moteus,pi3hat
Classifier: Development Status :: 3 - Alpha
Classifier: Intended Audience :: Developers
Classifier: License :: OSI Approved :: Apache Software License
Classifier: Programming Language :: Python :: 3
Requires-Python: >=3.7
Requires-Dist: moteus >=0.3.91
